{
  "username": "pkufranky",
  "areas": {
    "OSS": {
      "score": 0.3999999999999999,
      "details": {
        "issue_resolution_rate": 0.6,
        "pr_merge_rate": 0.5,
        "commits_activity": 1.0
      }
    },
    "Status": {
      "score": 0.39743589743589736,
      "details": {
        "lines_activity": 1.0,
        "commits_activity": 1.0,
        "week_streak": 0.09615384615384616
      }
    },
    "Sentiment": {
      "score": 0.0,
      "details": {
        "pkufranky/shellconf": -0.4519166666666667
      }
    },
    "Commitment": {
      "score": 0.6,
      "details": {
        "criteria_met": {
          "has_12_month_streak": false,
          "has_6_month_streak": true,
          "has_write_to_non_owned_repo": false,
          "has_repo_at_50th_percentile_commits": true,
          "at_75th_percentile_followers": true
        },
        "total_points": 3,
        "max_points": 5,
        "percentage": 60.0
      }
    }
  },
  "weights": {
    "OSS": 0.25,
    "Status": 0.25,
    "Sentiment": 0.25,
    "Commitment": 0.25
  },
  "final_score": 0.34935897435897434,
  "language_usage": {
    "error": null,
    "languages": {
      "Ruby": [
        47529,
        135
      ],
      "Perl": [
        1160,
        2
      ],
      "Shell": [
        16400,
        75
      ],
      "JavaScript": [
        3376,
        8
      ],
      "Python": [
        6073,
        28
      ],
      "Go": [
        123,
        3
      ],
      "C++": [
        83981,
        11
      ],
      "C": [
        29310,
        2
      ],
      "PHP": [
        7773,
        1
      ],
      "Java": [
        3046,
        0
      ],
      "Vim Script": [
        32343,
        36
      ],
      "Common Lisp": [
        21606,
        22
      ],
      "Scheme": [
        2449,
        2
      ],
      "Clojure": [
        2238,
        2
      ],
      "C#": [
        562,
        0
      ],
      "CoffeeScript": [
        26,
        0
      ],
      "Prolog": [
        1,
        0
      ],
      "Scala": [
        1,
        0
      ]
    },
    "language_count": 18,
    "total_commits": 327,
    "total_lines": 257997,
    "top_5_languages": [
      {
        "language": "Ruby",
        "lines": 47529,
        "commits": 135
      },
      {
        "language": "Shell",
        "lines": 16400,
        "commits": 75
      },
      {
        "language": "Vim Script",
        "lines": 32343,
        "commits": 36
      },
      {
        "language": "Python",
        "lines": 6073,
        "commits": 28
      },
      {
        "language": "Common Lisp",
        "lines": 21606,
        "commits": 22
      }
    ]
  },
  "import_scan": {
    "error": null,
    "username": "pkufranky",
    "analysis_date": "2026-02-23T19:13:10.704004",
    "total_repos_analyzed": 20,
    "total_files_analyzed": 282,
    "languages": {
      "C": {
        "files_scanned": 61,
        "packages": {
          "cache.h": 20,
          "JudyL.h": 17,
          "Judy1.h": 17,
          "JudyPrivate1L.h": 16,
          "builtin.h": 9,
          "parse-options.h": 8,
          "commit.h": 6,
          "zutil.h": 6,
          "Judy.h": 5,
          "limits.h": 5,
          "<limits.h>": 5,
          "stdio.h": 5,
          "<stdio.h>": 5,
          "blob.h": 4,
          "archive.h": 4,
          "diff.h": 4,
          "revision.h": 4,
          "JudyPrintJP.c": 4,
          "tag.h": 3,
          "quote.h": 3,
          "refs.h": 3,
          "cache-tree.h": 3,
          "stdlib.h": 3,
          "<stdlib.h>": 3,
          "inftrees.h": 3,
          "common.h": 3,
          "tree.h": 2,
          "attr.h": 2,
          "tree-walk.h": 2,
          "run-command.h": 2,
          "bisect.h": 2,
          "remote.h": 2,
          "branch.h": 2,
          "exec_cmd.h": 2,
          "dir.h": 2,
          "diffcore.h": 2,
          "string-list.h": 2,
          "<errno.h>": 2,
          "errno.h": 2,
          "Judy1Op.h": 2,
          "<ctype.h>": 2,
          "assert.h": 2,
          "ctype.h": 2,
          "<assert.h>": 2,
          "<locale/weight.h>": 2,
          "locale/weight.h": 2,
          "shlib-compat.h": 2,
          "<shlib-compat.h>": 2,
          "deflate.h": 2,
          "such": 2,
          "inffast.h": 2,
          "inflate.h": 2,
          "object.h": 1,
          "tar.h": 1,
          "unpack-trees.h": 1,
          "list-objects.h": 1,
          "log-tree.h": 1,
          "sha1-lookup.h": 1,
          "sha1.h": 1,
          "git-compat-util.h": 1,
          "delta.h": 1,
          "transport.h": 1,
          "pkt-line.h": 1,
          "sideband.h": 1,
          "xdiff-interface.h": 1,
          "utf8.h": 1,
          "mailmap.h": 1,
          "color.h": 1,
          "bundle.h": 1,
          "Judy1Dup.h": 1,
          "<string.h>": 1,
          "<stddef.h>": 1,
          "stddef.h": 1,
          "string.h": 1,
          "http_parser.h": 1,
          "PREG": 1,
          "POSIX": 1,
          "it": 1,
          "regexec.c": 1,
          "regex.h": 1,
          "regex_internal.h": 1,
          "config.h": 1,
          "regcomp.c": 1,
          "<regex.h>": 1,
          "regex_internal.c": 1,
          "crc32.h": 1,
          "inffixed.h": 1,
          "trees.h": 1
        }
      },
      "C++ Header": {
        "files_scanned": 20,
        "packages": {
          "catch_common.h": 5,
          "catch_tostring.h": 4,
          "catch_context.h": 4,
          "catch_expressionresult_builder.h": 3,
          "<string>": 3,
          "vector": 3,
          "string": 3,
          "<vector>": 3,
          "internal/catch_compiler_capabilities.h": 2,
          "internal/catch_default_main.hpp": 2,
          "<stdlib.h>": 2,
          "fstream": 2,
          "<fstream>": 2,
          "stdlib.h": 2,
          "<limits>": 2,
          "limits": 2,
          "catch_interfaces_config.h": 2,
          "catch_debugger.h": 2,
          "namespace": 2,
          "<iostream>": 2,
          "iostream": 2,
          "unistd.h": 2,
          "<unistd.h>": 2,
          "assert.h": 2,
          "<assert.h>": 2,
          "Catch::Detail::Approx": 1,
          "internal/catch_generators.hpp": 1,
          "internal/catch_interfaces_runner.h": 1,
          "internal/catch_context.h": 1,
          "internal/catch_notimplemented_exception.h": 1,
          "internal/catch_matchers.hpp": 1,
          "internal/catch_section.h": 1,
          "internal/catch_test_case_info.h": 1,
          "internal/catch_approx.hpp": 1,
          "internal/catch_interfaces_exception.h": 1,
          "internal/catch_test_registry.hpp": 1,
          "internal/catch_impl.hpp": 1,
          "internal/catch_capture.hpp": 1,
          "internal/catch_objc.hpp": 1,
          "internal/catch_test_spec.h": 1,
          "internal/catch_list.hpp": 1,
          "internal/catch_runner_impl.hpp": 1,
          "internal/catch_commandline.hpp": 1,
          "internal/catch_version.h": 1,
          "internal/catch_text.h": 1,
          "catch_runner.hpp": 1,
          "catch.hpp": 1,
          "cmath": 1,
          "<cmath>": 1,
          "catch_assertionresult.h": 1,
          "ostream": 1,
          "<ostream>": 1,
          "catch_message.h": 1,
          "catch_interfaces_capture.h": 1,
          "catch_interfaces_registry_hub.h": 1,
          "catch_expression_decomposer.hpp": 1,
          "catch_config.hpp": 1,
          "Clara": 1,
          "catch_clara.h": 1,
          "catch_test_spec.h": 1,
          "catch_stream.h": 1,
          "memory": 1,
          "<memory>": 1,
          "catch_console_colour.hpp": 1,
          "AfxWin.h": 1,
          "<windows.h>": 1,
          "windows.h": 1,
          "<AfxWin.h>": 1,
          "catch_runner_impl.hpp": 1,
          "catch_stream.hpp": 1,
          "<sys/sysctl.h>": 1,
          "sys/types.h": 1,
          "stdbool.h": 1,
          "sys/sysctl.h": 1,
          "<stdbool.h>": 1,
          "<sys/types.h>": 1,
          "<cstddef>": 1,
          "cstddef": 1,
          "Foundation/Foundation.h": 1,
          "catch_interfaces_exception.h": 1,
          "catch_expression_lhs.hpp": 1,
          "catch_evaluate.hpp": 1,
          "Generators": 1,
          "<iterator>": 1,
          "iterator": 1,
          "map": 1,
          "catch_interfaces_generators.h": 1,
          "<map>": 1
        }
      },
      "C/C++ Header": {
        "files_scanned": 20,
        "packages": {
          "<string>": 4,
          "string": 4,
          "stdlib.h": 4,
          "<stdlib.h>": 4,
          "stdio.h": 4,
          "<stdio.h>": 4,
          "sstream": 3,
          "vector": 3,
          "<sstream>": 3,
          "<vector>": 3,
          "<stdexcept>": 2,
          "memory": 2,
          "<algorithm>": 2,
          "<memory>": 2,
          "algorithm": 2,
          "stdexcept": 2,
          "catch_result_type.h": 2,
          "git-compat-util.h": 2,
          "Judy.h": 2,
          "assert.h": 2,
          "<assert.h>": 2,
          "<stdint.h>": 2,
          "sys/types.h": 2,
          "<sys/types.h>": 2,
          "stdint.h": 2,
          "<stddef.h>": 2,
          "stddef.h": 2,
          "<string.h>": 2,
          "string.h": 2,
          "malloc.h": 2,
          "<malloc.h>": 2,
          "CommonArgProperties<ConfigT>::placeholder": 1,
          "map": 1,
          "namespace": 1,
          "<map>": 1,
          "catch_compiler_capabilities.h": 1,
          "catch_ptr.hpp": 1,
          "catch_interfaces_generators.h": 1,
          "catch_platform.h": 1,
          "catch_assertionresult.h": 1,
          "catch_evaluate.hpp": 1,
          "catch_common.h": 1,
          "catch_tostring.h": 1,
          "object.h": 1,
          "notes.h": 1,
          "commit.h": 1,
          "cache.h": 1,
          "strbuf.h": 1,
          "<Judy.h>": 1,
          "inttypes.h": 1,
          "limits.h": 1,
          "<limits.h>": 1,
          "<inttypes.h>": 1,
          "JudyPrivate.h": 1,
          "JudyPrivateBranch.h": 1,
          "BaseTsd.h": 1,
          "<BaseTsd.h>": 1,
          "<ctype.h>": 1,
          "ctype.h": 1,
          "<wctype.h>": 1,
          "wchar.h": 1,
          "<locale/localeinfo.h>": 1,
          "<locale/elem-hash.h>": 1,
          "mbsupport.h": 1,
          "locale/elem-hash.h": 1,
          "<wchar.h>": 1,
          "locale.h": 1,
          "<langinfo.h>": 1,
          "locale/weight.h": 1,
          "bits/libc-lock.h": 1,
          "<locale/coll-lookup.h>": 1,
          "<locale/weight.h>": 1,
          "langinfo.h": 1,
          "locale/coll-lookup.h": 1,
          "libintl.h": 1,
          "wctype.h": 1,
          "locale/localeinfo.h": 1,
          "alloca.h": 1,
          "<stdbool.h>": 1,
          "<alloca.h>": 1,
          "stdbool.h": 1,
          "<locale.h>": 1,
          "<bits/libc-lock.h>": 1,
          "<libintl.h>": 1,
          "zutil.h": 1,
          "content": 1,
          "and": 1,
          "default": 1,
          "these": 1,
          "zconf.h": 1,
          "ensures": 1,
          "strm->next_in": 1,
          "unix.h": 1,
          "alloc.h": 1,
          "zlib.h": 1,
          "<alloc.h>": 1,
          "<unix.h>": 1
        }
      },
      "Go": {
        "files_scanned": 15,
        "packages": {
          "C": 9,
          "fmt": 5,
          "unsafe": 3,
          "os": 3,
          "bytes": 2,
          "testing": 2,
          "time": 2,
          "flag": 2,
          "io": 1,
          "reflect": 1,
          "rocksdb/c.h": 1,
          "<stdlib.h>": 1,
          "math/rand": 1,
          "path/filepath": 1,
          "exec": 1,
          "GOROOT_FINAL": 1,
          "runtime": 1,
          "strings": 1,
          "386": 1,
          "amd64": 1,
          "whether": 1,
          "arm": 1,
          "systems": 1,
          "path": 1
        }
      },
      "Perl": {
        "files_scanned": 1,
        "packages": {
          "strict": 1,
          "warnings": 1,
          "File::Find": 1
        }
      },
      "Python": {
        "files_scanned": 59,
        "packages": {
          "logging": 31,
          "os": 24,
          "gitosis": 16,
          "kafka": 16,
          "ConfigParser": 14,
          "nose": 12,
          "sys": 11,
          "eq_": 10,
          "six": 10,
          "time": 9,
          "errno": 8,
          "util": 8,
          "RawConfigParser": 8,
          "collections": 8,
          "threading": 8,
          "__future__": 7,
          "absolute_import": 7,
          "repository": 6,
          "thrift": 6,
          "struct": 6,
          "NoSectionError": 5,
          "cStringIO": 5,
          "StringIO": 5,
          "re": 5,
          "Queue": 5,
          "KafkaClient": 5,
          "subprocess": 4,
          "random": 4,
          "itertools": 4,
          "xrange": 4,
          "Empty": 4,
          "test": 4,
          "app": 3,
          "ssh": 3,
          "gitweb": 3,
          "shutil": 3,
          "gitdaemon": 3,
          "setuptools": 3,
          "numbers": 3,
          "TBinaryProtocol": 3,
          "TType": 3,
          "socket": 3,
          "SimpleProducer": 3,
          "SimpleConsumer": 3,
          "copy": 3,
          "queue": 3,
          "multiprocessing": 3,
          "group": 2,
          "urllib": 2,
          "pkg_resources": 2,
          "access": 2,
          "maketemp": 2,
          "mkdir": 2,
          "init": 2,
          "assert_raises": 2,
          "setup": 2,
          "Integral": 2,
          "defaultdict": 2,
          "ttypes": 2,
          "*": 2,
          "TTransport": 2,
          "fastbinary": 2,
          "happybase": 2,
          "KafkaConnection": 2,
          "KafkaProtocol": 2,
          "binascii": 2,
          "Process": 2,
          "cycle": 2,
          "fnmatch": 1,
          "optparse": 1,
          "run_hook": 1,
          "resource_filename": 1,
          "serve": 1,
          "stat": 1,
          "TBufferedTransport": 1,
          "TSocket": 1,
          "a": 1,
          "TProcessor": 1,
          "contextlib": 1,
          "TException": 1,
          "operator": 1,
          "attrgetter": 1,
          "Struct": 1,
          "the": 1,
          "OrderedDict": 1,
          "ordereddict": 1,
          "requirements": 1,
          "find_packages": 1,
          "join": 1,
          "Connection": 1,
          "faulthandler": 1,
          "signal": 1,
          "TTransportException": 1,
          "assert_equal": 1,
          "RoundRobinPartitioner": 1,
          "functools": 1,
          "collect_hosts": 1,
          "snappy": 1,
          "io": 1,
          "gzip": 1,
          "BytesIO": 1,
          "namedtuple": 1,
          "ConnectionError": 1,
          "local": 1,
          "shuffle": 1,
          "Lock": 1,
          "ReentrantTimer": 1,
          "zip_longest": 1,
          "izip_longest": 1,
          "getLogger": 1,
          "check_error": 1,
          "CODEC_NONE": 1,
          "HashedPartitioner": 1,
          "Thread": 1,
          "BufferUnderflowError": 1,
          "tox": 1,
          "unittest2": 1,
          "unittest": 1,
          "uuid": 1,
          "get_open_port": 1,
          "ExternalService": 1,
          "urlparse": 1,
          "tempfile": 1,
          "select": 1,
          "mock": 1,
          "sleep": 1,
          "ANY": 1,
          "Timer": 1,
          "ZookeeperFixture": 1,
          "random_string": 1
        }
      },
      "Ruby": {
        "files_scanned": 28,
        "packages": {
          "Haml::Util": 4,
          "strscan": 4,
          "apache2": 3,
          "rubygems": 3,
          "haml/engine": 3,
          "haml/util": 3,
          "haml/version": 2,
          "Haml::Helpers": 2,
          "fileutils": 2,
          "sass/plugin": 2,
          "stringio": 2,
          "cgi": 2,
          "haml/shared": 2,
          "haml/template/options": 2,
          "set": 2,
          "sass/tree/node": 2,
          "python": 1,
          "apache2::mod_deflate": 1,
          "apache2::mod_rewrite": 1,
          "apache2::mod_headers": 1,
          "apache2::#{recipe_name}": 1,
          "pacman": 1,
          "sinatra": 1,
          "json": 1,
          "lib": 1,
          "haml": 1,
          "haml/railtie": 1,
          "haml/helpers": 1,
          "haml/error": 1,
          "haml/buffer": 1,
          "Precompiler": 1,
          "haml/precompiler": 1,
          "haml/filters": 1,
          "haml/html": 1,
          "sass/repl": 1,
          "--trace": 1,
          "rbconfig": 1,
          "sass/css": 1,
          "sass": 1,
          "optparse": 1,
          "sass/less": 1,
          "@required": 1,
          "Haml::Filters::Base": 1,
          "Base": 1,
          "ActionViewExtensions": 1,
          "hpricot": 1,
          "Haml::HTML::Node": 1,
          "haml/html/erb": 1,
          "erubis": 1,
          "ruby_parser": 1,
          "<!--#{conditional}": 1,
          "sass/plugin/configuration": 1,
          "haml/helpers/action_view_mods": 1,
          "haml/helpers/action_view_extensions": 1,
          "haml/helpers/xss_mods": 1,
          "haml/template/plugin": 1,
          "haml/template/patch": 1,
          "Haml::Util.av_template_class": 1,
          "erb": 1,
          "action_pack": 1,
          "haml/root": 1,
          "haml/util/subset_map": 1,
          "enumerator": 1,
          "sass/engine": 1,
          "sass/scss/css_parser": 1,
          "sass/tree/import_node": 1,
          "sass/script": 1,
          "sass/tree/for_node": 1,
          "digest/sha1": 1,
          "sass/tree/extend_node": 1,
          "sass/tree/while_node": 1,
          "sass/tree/prop_node": 1,
          "sass/files": 1,
          "sass/tree/directive_node": 1,
          "sass/environment": 1,
          "sass/scss": 1,
          "sass/tree/comment_node": 1,
          "sass/tree/rule_node": 1,
          "sass/tree/root_node": 1,
          "sass/tree/mixin_node": 1,
          "sass/tree/mixin_def_node": 1,
          "sass/tree/if_node": 1,
          "sass/tree/warn_node": 1,
          "sass/selector": 1,
          "MIXIN_DEFINITION_CHAR": 1,
          "sass/tree/variable_node": 1,
          "sass/error": 1,
          "sass/tree/debug_node": 1
        }
      }
    },
    "repositories": [
      {
        "repository": "pkufranky/Catch",
        "files_analyzed": 30,
        "languages_found": [
          "C++ Header",
          "C/C++ Header"
        ]
      },
      {
        "repository": "pkufranky/chef-repo",
        "files_analyzed": 30,
        "languages_found": [
          "Perl",
          "Ruby"
        ]
      },
      {
        "repository": "pkufranky/git",
        "files_analyzed": 30,
        "languages_found": [
          "C",
          "C/C++ Header"
        ]
      },
      {
        "repository": "pkufranky/gitosis",
        "files_analyzed": 24,
        "languages_found": [
          "Python"
        ]
      },
      {
        "repository": "pkufranky/gorocks",
        "files_analyzed": 12,
        "languages_found": [
          "Go"
        ]
      },
      {
        "repository": "pkufranky/goscript",
        "files_analyzed": 1,
        "languages_found": [
          "Go"
        ]
      },
      {
        "repository": "pkufranky/goscripts",
        "files_analyzed": 3,
        "languages_found": [
          "Go"
        ]
      },
      {
        "repository": "pkufranky/haml",
        "files_analyzed": 30,
        "languages_found": [
          "Ruby"
        ]
      },
      {
        "repository": "pkufranky/happybase",
        "files_analyzed": 15,
        "languages_found": [
          "Python"
        ]
      },
      {
        "repository": "pkufranky/judy",
        "files_analyzed": 30,
        "languages_found": [
          "C",
          "C/C++ Header"
        ]
      },
      {
        "repository": "pkufranky/kafka-python",
        "files_analyzed": 30,
        "languages_found": [
          "Python"
        ]
      },
      {
        "repository": "pkufranky/libgit2",
        "files_analyzed": 30,
        "languages_found": [
          "C",
          "C/C++ Header"
        ]
      }
    ]
  }
}