{
  "username": "sergeyk",
  "areas": {
    "OSS": {
      "score": 1.0,
      "details": {
        "issue_resolution_rate": 0.9032258064516129,
        "pr_merge_rate": 1.8387096774193548,
        "commits_activity": 1.0
      }
    },
    "Status": {
      "score": 0.33333333333333326,
      "details": {
        "lines_activity": 1.0,
        "commits_activity": 1.0,
        "week_streak": 0.0
      }
    },
    "Sentiment": {
      "score": 0.875,
      "details": {
        "sergeyk/anytime_recognition": 0.61505,
        "sergeyk/csrec": 0.437325,
        "sergeyk/model-comparison": 0.0726,
        "sergeyk/selective_search_ijcv_with_python": -0.07356,
        "sergeyk/timely": 0.23255625000000002,
        "sergeyk/vislab": 0.1899357142857143,
        "sergeyk/worldfaces": 0.4939,
        "sergeyk/x-backup": 0.3834666666666667
      }
    },
    "Commitment": {
      "score": 0.8,
      "details": {
        "criteria_met": {
          "has_12_month_streak": true,
          "has_6_month_streak": true,
          "has_write_to_non_owned_repo": false,
          "has_repo_at_50th_percentile_commits": true,
          "at_75th_percentile_followers": true
        },
        "total_points": 4,
        "max_points": 5,
        "percentage": 80.0
      }
    }
  },
  "weights": {
    "OSS": 0.25,
    "Status": 0.25,
    "Sentiment": 0.25,
    "Commitment": 0.25
  },
  "final_score": 0.7520833333333333,
  "language_usage": {
    "error": null,
    "languages": {
      "Python": [
        662491,
        190
      ],
      "MATLAB": [
        169907,
        37
      ],
      "Shell": [
        5910,
        1
      ],
      "JavaScript": [
        142665,
        29
      ],
      "Perl": [
        24444,
        0
      ],
      "TeX": [
        165314,
        109
      ],
      "CSS": [
        75962,
        18
      ],
      "Processing": [
        988,
        0
      ],
      "Ruby": [
        732,
        0
      ],
      "Jupyter Notebook": [
        353495,
        265
      ],
      "Dockerfile": [
        56,
        0
      ],
      "HTML": [
        135205,
        114
      ],
      "OpenEdge ABL": [
        572,
        0
      ],
      "Java": [
        394,
        0
      ],
      "PHP": [
        17,
        0
      ],
      "Makefile": [
        26032,
        13
      ],
      "C++": [
        453669,
        260
      ],
      "C": [
        489158,
        113
      ],
      "Awk": [
        459,
        0
      ],
      "Objective-C": [
        8723,
        1
      ],
      "M": [
        7221,
        1
      ],
      "Clean": [
        2567,
        0
      ],
      "Mercury": [
        160,
        0
      ]
    },
    "language_count": 23,
    "total_commits": 1151,
    "total_lines": 2726141,
    "top_5_languages": [
      {
        "language": "Jupyter Notebook",
        "lines": 353495,
        "commits": 265
      },
      {
        "language": "C++",
        "lines": 453669,
        "commits": 260
      },
      {
        "language": "Python",
        "lines": 662491,
        "commits": 190
      },
      {
        "language": "HTML",
        "lines": 135205,
        "commits": 114
      },
      {
        "language": "C",
        "lines": 489158,
        "commits": 113
      }
    ]
  },
  "import_scan": {
    "error": "list index out of range",
    "username": "sergeyk",
    "analysis_date": null,
    "total_repos_analyzed": 0,
    "total_files_analyzed": 0,
    "languages": {},
    "repositories": []
  }
}